ldh_client/__init__.py
ldh_client/common.py
ldh_client/liberty.py
ldh_client/nautilus_files_setup.py
ldh_client/nm_tunnel_setup.py
ldh_client/data/default.strict.yaml
ldh_client/data/one.liberty.debug.desktop
ldh_client/data/one.liberty.tunnel.desktop
ldh_client-0.0.11.dist-info/COPYING.AGPL.md
ldh_client-0.0.11.dist-info/COPYING.md
ldh_client-0.0.11.dist-info/METADATA
ldh_client-0.0.11.dist-info/WHEEL
ldh_client-0.0.11.dist-info/entry_points.txt
ldh_client-0.0.11.dist-info/top_level.txt
ldh_client-0.0.11.dist-info/RECORD
