Metadata-Version: 2.1
Name: ldh-client
Version: 0.0.11
Summary: Liberty CLI is a user-facing command-line client for interacting with Librem One or another Liberty Deckplan Host (LDH).
Home-page: https://source.puri.sm/liberty/tool/client
Author: Purism SPC
Author-email: doublerainbows@librem.one
License: AGPL-3.0-or-later
Platform: UNKNOWN
Classifier: Programming Language :: Python :: 3
Classifier: Programming Language :: Python :: 3.7
Classifier: Programming Language :: Python :: 3.8
Classifier: Programming Language :: Python :: 3.9
Classifier: License :: OSI Approved :: GNU Affero General Public License v3 or later (AGPLv3+)
Requires-Dist: click (<8.0,>=7.0)
Requires-Dist: distro (<2.0,>=1.3.0)
Requires-Dist: requests (<3.0,>=2.21.0)
Requires-Dist: ruamel.yaml (<1.0,>=0.15.34)
Requires-Dist: sh (<2.0,>=1.12.14)
Requires-Dist: PyGObject (<4.0,>=3.32.0)
